README.md
setup.cfg
setup.py
dataproc/__init__.py
dataproc.egg-info/PKG-INFO
dataproc.egg-info/SOURCES.txt
dataproc.egg-info/dependency_links.txt
dataproc.egg-info/requires.txt
dataproc.egg-info/top_level.txt
dataproc/executor/__init__.py
dataproc/model/__init__.py
dataproc/pipeline/__init__.py