Metadata-Version: 1.1
Name: dataproc
Version: 0.0.1
Summary: Data Processing and Transformation
Home-page: https://github.com/Delpinos/dataproc
Author: Alef Bruno Delpino
Author-email: alefdelpino@gmail.com
License: GPL License
Keywords: dataproc proc data etl tramsform process pipeline executor
Platform: UNKNOWN
Classifier: Programming Language :: Python :: 3.6
